<?xml version="1.0" encoding="UTF-8" ?>
<!DOCTYPE mapper PUBLIC "-//mybatis.org//DTD Mapper 3.0//EN" "http://mybatis.org/dtd/mybatis-3-mapper.dtd" >
<mapper namespace="com.rent.dao.PbcatcolMapper" >
  <resultMap id="BaseResultMap" type="com.rent.entity.Pbcatcol" >
    <!--
      WARNING - @mbggenerated
      This element is automatically generated by MyBatis Generator, do not modify.
      This element was generated on Mon Apr 24 14:56:49 CST 2017.
    -->
    <id column="ID" property="id" jdbcType="DECIMAL" />
    <result column="PBC_TNAM" property="pbcTnam" jdbcType="CHAR" />
    <result column="PBC_TID" property="pbcTid" jdbcType="DECIMAL" />
    <result column="PBC_OWNR" property="pbcOwnr" jdbcType="CHAR" />
    <result column="PBC_CNAM" property="pbcCnam" jdbcType="CHAR" />
    <result column="PBC_CID" property="pbcCid" jdbcType="DECIMAL" />
    <result column="PBC_LABL" property="pbcLabl" jdbcType="VARCHAR" />
    <result column="PBC_LPOS" property="pbcLpos" jdbcType="DECIMAL" />
    <result column="PBC_HDR" property="pbcHdr" jdbcType="VARCHAR" />
    <result column="PBC_HPOS" property="pbcHpos" jdbcType="DECIMAL" />
    <result column="PBC_JTFY" property="pbcJtfy" jdbcType="DECIMAL" />
    <result column="PBC_MASK" property="pbcMask" jdbcType="VARCHAR" />
    <result column="PBC_CASE" property="pbcCase" jdbcType="DECIMAL" />
    <result column="PBC_HGHT" property="pbcHght" jdbcType="DECIMAL" />
    <result column="PBC_WDTH" property="pbcWdth" jdbcType="DECIMAL" />
    <result column="PBC_PTRN" property="pbcPtrn" jdbcType="VARCHAR" />
    <result column="PBC_BMAP" property="pbcBmap" jdbcType="CHAR" />
    <result column="PBC_INIT" property="pbcInit" jdbcType="VARCHAR" />
    <result column="PBC_CMNT" property="pbcCmnt" jdbcType="VARCHAR" />
    <result column="PBC_EDIT" property="pbcEdit" jdbcType="VARCHAR" />
    <result column="PBC_TAG" property="pbcTag" jdbcType="VARCHAR" />
  </resultMap>
  <sql id="Base_Column_List" >
    <!--
      WARNING - @mbggenerated
      This element is automatically generated by MyBatis Generator, do not modify.
      This element was generated on Mon Apr 24 14:56:49 CST 2017.
    -->
    ID, PBC_TNAM, PBC_TID, PBC_OWNR, PBC_CNAM, PBC_CID, PBC_LABL, PBC_LPOS, PBC_HDR, 
    PBC_HPOS, PBC_JTFY, PBC_MASK, PBC_CASE, PBC_HGHT, PBC_WDTH, PBC_PTRN, PBC_BMAP, PBC_INIT, 
    PBC_CMNT, PBC_EDIT, PBC_TAG
  </sql>
  <select id="selectByPrimaryKey" resultMap="BaseResultMap" parameterType="java.lang.Integer" >
    <!--
      WARNING - @mbggenerated
      This element is automatically generated by MyBatis Generator, do not modify.
      This element was generated on Mon Apr 24 14:56:49 CST 2017.
    -->
    select 
    <include refid="Base_Column_List" />
    from PBCATCOL
    where ID = #{id,jdbcType=DECIMAL}
  </select>
  <delete id="deleteByPrimaryKey" parameterType="java.lang.Integer" >
    <!--
      WARNING - @mbggenerated
      This element is automatically generated by MyBatis Generator, do not modify.
      This element was generated on Mon Apr 24 14:56:49 CST 2017.
    -->
    delete from PBCATCOL
    where ID = #{id,jdbcType=DECIMAL}
  </delete>
  <insert id="insert" parameterType="com.rent.entity.Pbcatcol" >
    <!--
      WARNING - @mbggenerated
      This element is automatically generated by MyBatis Generator, do not modify.
      This element was generated on Mon Apr 24 14:56:49 CST 2017.
    -->
    insert into PBCATCOL (ID, PBC_TNAM, PBC_TID, 
      PBC_OWNR, PBC_CNAM, PBC_CID, 
      PBC_LABL, PBC_LPOS, PBC_HDR, 
      PBC_HPOS, PBC_JTFY, PBC_MASK, 
      PBC_CASE, PBC_HGHT, PBC_WDTH, 
      PBC_PTRN, PBC_BMAP, PBC_INIT, 
      PBC_CMNT, PBC_EDIT, PBC_TAG
      )
    values (#{id,jdbcType=DECIMAL}, #{pbcTnam,jdbcType=CHAR}, #{pbcTid,jdbcType=DECIMAL}, 
      #{pbcOwnr,jdbcType=CHAR}, #{pbcCnam,jdbcType=CHAR}, #{pbcCid,jdbcType=DECIMAL}, 
      #{pbcLabl,jdbcType=VARCHAR}, #{pbcLpos,jdbcType=DECIMAL}, #{pbcHdr,jdbcType=VARCHAR}, 
      #{pbcHpos,jdbcType=DECIMAL}, #{pbcJtfy,jdbcType=DECIMAL}, #{pbcMask,jdbcType=VARCHAR}, 
      #{pbcCase,jdbcType=DECIMAL}, #{pbcHght,jdbcType=DECIMAL}, #{pbcWdth,jdbcType=DECIMAL}, 
      #{pbcPtrn,jdbcType=VARCHAR}, #{pbcBmap,jdbcType=CHAR}, #{pbcInit,jdbcType=VARCHAR}, 
      #{pbcCmnt,jdbcType=VARCHAR}, #{pbcEdit,jdbcType=VARCHAR}, #{pbcTag,jdbcType=VARCHAR}
      )
  </insert>
  <insert id="insertSelective" parameterType="com.rent.entity.Pbcatcol" >
    <!--
      WARNING - @mbggenerated
      This element is automatically generated by MyBatis Generator, do not modify.
      This element was generated on Mon Apr 24 14:56:49 CST 2017.
    -->
    insert into PBCATCOL
    <trim prefix="(" suffix=")" suffixOverrides="," >
      <if test="id != null" >
        ID,
      </if>
      <if test="pbcTnam != null" >
        PBC_TNAM,
      </if>
      <if test="pbcTid != null" >
        PBC_TID,
      </if>
      <if test="pbcOwnr != null" >
        PBC_OWNR,
      </if>
      <if test="pbcCnam != null" >
        PBC_CNAM,
      </if>
      <if test="pbcCid != null" >
        PBC_CID,
      </if>
      <if test="pbcLabl != null" >
        PBC_LABL,
      </if>
      <if test="pbcLpos != null" >
        PBC_LPOS,
      </if>
      <if test="pbcHdr != null" >
        PBC_HDR,
      </if>
      <if test="pbcHpos != null" >
        PBC_HPOS,
      </if>
      <if test="pbcJtfy != null" >
        PBC_JTFY,
      </if>
      <if test="pbcMask != null" >
        PBC_MASK,
      </if>
      <if test="pbcCase != null" >
        PBC_CASE,
      </if>
      <if test="pbcHght != null" >
        PBC_HGHT,
      </if>
      <if test="pbcWdth != null" >
        PBC_WDTH,
      </if>
      <if test="pbcPtrn != null" >
        PBC_PTRN,
      </if>
      <if test="pbcBmap != null" >
        PBC_BMAP,
      </if>
      <if test="pbcInit != null" >
        PBC_INIT,
      </if>
      <if test="pbcCmnt != null" >
        PBC_CMNT,
      </if>
      <if test="pbcEdit != null" >
        PBC_EDIT,
      </if>
      <if test="pbcTag != null" >
        PBC_TAG,
      </if>
    </trim>
    <trim prefix="values (" suffix=")" suffixOverrides="," >
      <if test="id != null" >
        #{id,jdbcType=DECIMAL},
      </if>
      <if test="pbcTnam != null" >
        #{pbcTnam,jdbcType=CHAR},
      </if>
      <if test="pbcTid != null" >
        #{pbcTid,jdbcType=DECIMAL},
      </if>
      <if test="pbcOwnr != null" >
        #{pbcOwnr,jdbcType=CHAR},
      </if>
      <if test="pbcCnam != null" >
        #{pbcCnam,jdbcType=CHAR},
      </if>
      <if test="pbcCid != null" >
        #{pbcCid,jdbcType=DECIMAL},
      </if>
      <if test="pbcLabl != null" >
        #{pbcLabl,jdbcType=VARCHAR},
      </if>
      <if test="pbcLpos != null" >
        #{pbcLpos,jdbcType=DECIMAL},
      </if>
      <if test="pbcHdr != null" >
        #{pbcHdr,jdbcType=VARCHAR},
      </if>
      <if test="pbcHpos != null" >
        #{pbcHpos,jdbcType=DECIMAL},
      </if>
      <if test="pbcJtfy != null" >
        #{pbcJtfy,jdbcType=DECIMAL},
      </if>
      <if test="pbcMask != null" >
        #{pbcMask,jdbcType=VARCHAR},
      </if>
      <if test="pbcCase != null" >
        #{pbcCase,jdbcType=DECIMAL},
      </if>
      <if test="pbcHght != null" >
        #{pbcHght,jdbcType=DECIMAL},
      </if>
      <if test="pbcWdth != null" >
        #{pbcWdth,jdbcType=DECIMAL},
      </if>
      <if test="pbcPtrn != null" >
        #{pbcPtrn,jdbcType=VARCHAR},
      </if>
      <if test="pbcBmap != null" >
        #{pbcBmap,jdbcType=CHAR},
      </if>
      <if test="pbcInit != null" >
        #{pbcInit,jdbcType=VARCHAR},
      </if>
      <if test="pbcCmnt != null" >
        #{pbcCmnt,jdbcType=VARCHAR},
      </if>
      <if test="pbcEdit != null" >
        #{pbcEdit,jdbcType=VARCHAR},
      </if>
      <if test="pbcTag != null" >
        #{pbcTag,jdbcType=VARCHAR},
      </if>
    </trim>
  </insert>
  <update id="updateByPrimaryKeySelective" parameterType="com.rent.entity.Pbcatcol" >
    <!--
      WARNING - @mbggenerated
      This element is automatically generated by MyBatis Generator, do not modify.
      This element was generated on Mon Apr 24 14:56:49 CST 2017.
    -->
    update PBCATCOL
    <set >
      <if test="pbcTnam != null" >
        PBC_TNAM = #{pbcTnam,jdbcType=CHAR},
      </if>
      <if test="pbcTid != null" >
        PBC_TID = #{pbcTid,jdbcType=DECIMAL},
      </if>
      <if test="pbcOwnr != null" >
        PBC_OWNR = #{pbcOwnr,jdbcType=CHAR},
      </if>
      <if test="pbcCnam != null" >
        PBC_CNAM = #{pbcCnam,jdbcType=CHAR},
      </if>
      <if test="pbcCid != null" >
        PBC_CID = #{pbcCid,jdbcType=DECIMAL},
      </if>
      <if test="pbcLabl != null" >
        PBC_LABL = #{pbcLabl,jdbcType=VARCHAR},
      </if>
      <if test="pbcLpos != null" >
        PBC_LPOS = #{pbcLpos,jdbcType=DECIMAL},
      </if>
      <if test="pbcHdr != null" >
        PBC_HDR = #{pbcHdr,jdbcType=VARCHAR},
      </if>
      <if test="pbcHpos != null" >
        PBC_HPOS = #{pbcHpos,jdbcType=DECIMAL},
      </if>
      <if test="pbcJtfy != null" >
        PBC_JTFY = #{pbcJtfy,jdbcType=DECIMAL},
      </if>
      <if test="pbcMask != null" >
        PBC_MASK = #{pbcMask,jdbcType=VARCHAR},
      </if>
      <if test="pbcCase != null" >
        PBC_CASE = #{pbcCase,jdbcType=DECIMAL},
      </if>
      <if test="pbcHght != null" >
        PBC_HGHT = #{pbcHght,jdbcType=DECIMAL},
      </if>
      <if test="pbcWdth != null" >
        PBC_WDTH = #{pbcWdth,jdbcType=DECIMAL},
      </if>
      <if test="pbcPtrn != null" >
        PBC_PTRN = #{pbcPtrn,jdbcType=VARCHAR},
      </if>
      <if test="pbcBmap != null" >
        PBC_BMAP = #{pbcBmap,jdbcType=CHAR},
      </if>
      <if test="pbcInit != null" >
        PBC_INIT = #{pbcInit,jdbcType=VARCHAR},
      </if>
      <if test="pbcCmnt != null" >
        PBC_CMNT = #{pbcCmnt,jdbcType=VARCHAR},
      </if>
      <if test="pbcEdit != null" >
        PBC_EDIT = #{pbcEdit,jdbcType=VARCHAR},
      </if>
      <if test="pbcTag != null" >
        PBC_TAG = #{pbcTag,jdbcType=VARCHAR},
      </if>
    </set>
    where ID = #{id,jdbcType=DECIMAL}
  </update>
  <update id="updateByPrimaryKey" parameterType="com.rent.entity.Pbcatcol" >
    <!--
      WARNING - @mbggenerated
      This element is automatically generated by MyBatis Generator, do not modify.
      This element was generated on Mon Apr 24 14:56:49 CST 2017.
    -->
    update PBCATCOL
    set PBC_TNAM = #{pbcTnam,jdbcType=CHAR},
      PBC_TID = #{pbcTid,jdbcType=DECIMAL},
      PBC_OWNR = #{pbcOwnr,jdbcType=CHAR},
      PBC_CNAM = #{pbcCnam,jdbcType=CHAR},
      PBC_CID = #{pbcCid,jdbcType=DECIMAL},
      PBC_LABL = #{pbcLabl,jdbcType=VARCHAR},
      PBC_LPOS = #{pbcLpos,jdbcType=DECIMAL},
      PBC_HDR = #{pbcHdr,jdbcType=VARCHAR},
      PBC_HPOS = #{pbcHpos,jdbcType=DECIMAL},
      PBC_JTFY = #{pbcJtfy,jdbcType=DECIMAL},
      PBC_MASK = #{pbcMask,jdbcType=VARCHAR},
      PBC_CASE = #{pbcCase,jdbcType=DECIMAL},
      PBC_HGHT = #{pbcHght,jdbcType=DECIMAL},
      PBC_WDTH = #{pbcWdth,jdbcType=DECIMAL},
      PBC_PTRN = #{pbcPtrn,jdbcType=VARCHAR},
      PBC_BMAP = #{pbcBmap,jdbcType=CHAR},
      PBC_INIT = #{pbcInit,jdbcType=VARCHAR},
      PBC_CMNT = #{pbcCmnt,jdbcType=VARCHAR},
      PBC_EDIT = #{pbcEdit,jdbcType=VARCHAR},
      PBC_TAG = #{pbcTag,jdbcType=VARCHAR}
    where ID = #{id,jdbcType=DECIMAL}
  </update>
</mapper>