<?xml version="1.0" encoding="UTF-8" ?>
<!DOCTYPE mapper PUBLIC "-//mybatis.org//DTD Mapper 3.0//EN" "http://mybatis.org/dtd/mybatis-3-mapper.dtd" >
<mapper namespace="com.rent.dao.PrhDevTmp2Mapper" >
  <resultMap id="BaseResultMap" type="com.rent.entity.PrhDevTmp2" >
    <!--
      WARNING - @mbggenerated
      This element is automatically generated by MyBatis Generator, do not modify.
      This element was generated on Mon Apr 24 14:56:49 CST 2017.
    -->
    <id column="ID" property="id" jdbcType="DECIMAL" />
    <result column="BUILD" property="build" jdbcType="VARCHAR" />
    <result column="ROOMNO" property="roomno" jdbcType="VARCHAR" />
    <result column="FLOOR" property="floor" jdbcType="VARCHAR" />
    <result column="TYPE" property="type" jdbcType="VARCHAR" />
    <result column="AREA" property="area" jdbcType="DECIMAL" />
    <result column="RATE" property="rate" jdbcType="DECIMAL" />
    <result column="PRICE" property="price" jdbcType="DECIMAL" />
    <result column="VTYPE" property="vtype" jdbcType="VARCHAR" />
    <result column="VROOMNO" property="vroomno" jdbcType="VARCHAR" />
    <result column="V1" property="v1" jdbcType="DECIMAL" />
    <result column="V2" property="v2" jdbcType="DECIMAL" />
    <result column="V3" property="v3" jdbcType="DECIMAL" />
    <result column="V4" property="v4" jdbcType="DECIMAL" />
    <result column="V5" property="v5" jdbcType="DECIMAL" />
    <result column="V6" property="v6" jdbcType="DECIMAL" />
    <result column="V7" property="v7" jdbcType="DECIMAL" />
    <result column="V8" property="v8" jdbcType="DECIMAL" />
    <result column="V9" property="v9" jdbcType="DECIMAL" />
    <result column="V10" property="v10" jdbcType="DECIMAL" />
  </resultMap>
  <sql id="Base_Column_List" >
    <!--
      WARNING - @mbggenerated
      This element is automatically generated by MyBatis Generator, do not modify.
      This element was generated on Mon Apr 24 14:56:49 CST 2017.
    -->
    ID, BUILD, ROOMNO, FLOOR, TYPE, AREA, RATE, PRICE, VTYPE, VROOMNO, V1, V2, V3, V4, 
    V5, V6, V7, V8, V9, V10
  </sql>
  <select id="selectByPrimaryKey" resultMap="BaseResultMap" parameterType="java.lang.Integer" >
    <!--
      WARNING - @mbggenerated
      This element is automatically generated by MyBatis Generator, do not modify.
      This element was generated on Mon Apr 24 14:56:49 CST 2017.
    -->
    select 
    <include refid="Base_Column_List" />
    from PRH_DEV_TMP2
    where ID = #{id,jdbcType=DECIMAL}
  </select>
  <delete id="deleteByPrimaryKey" parameterType="java.lang.Integer" >
    <!--
      WARNING - @mbggenerated
      This element is automatically generated by MyBatis Generator, do not modify.
      This element was generated on Mon Apr 24 14:56:49 CST 2017.
    -->
    delete from PRH_DEV_TMP2
    where ID = #{id,jdbcType=DECIMAL}
  </delete>
  <insert id="insert" parameterType="com.rent.entity.PrhDevTmp2" >
    <!--
      WARNING - @mbggenerated
      This element is automatically generated by MyBatis Generator, do not modify.
      This element was generated on Mon Apr 24 14:56:49 CST 2017.
    -->
    insert into PRH_DEV_TMP2 (ID, BUILD, ROOMNO, 
      FLOOR, TYPE, AREA, 
      RATE, PRICE, VTYPE, 
      VROOMNO, V1, V2, V3, 
      V4, V5, V6, V7, 
      V8, V9, V10)
    values (#{id,jdbcType=DECIMAL}, #{build,jdbcType=VARCHAR}, #{roomno,jdbcType=VARCHAR}, 
      #{floor,jdbcType=VARCHAR}, #{type,jdbcType=VARCHAR}, #{area,jdbcType=DECIMAL}, 
      #{rate,jdbcType=DECIMAL}, #{price,jdbcType=DECIMAL}, #{vtype,jdbcType=VARCHAR}, 
      #{vroomno,jdbcType=VARCHAR}, #{v1,jdbcType=DECIMAL}, #{v2,jdbcType=DECIMAL}, #{v3,jdbcType=DECIMAL}, 
      #{v4,jdbcType=DECIMAL}, #{v5,jdbcType=DECIMAL}, #{v6,jdbcType=DECIMAL}, #{v7,jdbcType=DECIMAL}, 
      #{v8,jdbcType=DECIMAL}, #{v9,jdbcType=DECIMAL}, #{v10,jdbcType=DECIMAL})
  </insert>
  <insert id="insertSelective" parameterType="com.rent.entity.PrhDevTmp2" >
    <!--
      WARNING - @mbggenerated
      This element is automatically generated by MyBatis Generator, do not modify.
      This element was generated on Mon Apr 24 14:56:49 CST 2017.
    -->
    insert into PRH_DEV_TMP2
    <trim prefix="(" suffix=")" suffixOverrides="," >
      <if test="id != null" >
        ID,
      </if>
      <if test="build != null" >
        BUILD,
      </if>
      <if test="roomno != null" >
        ROOMNO,
      </if>
      <if test="floor != null" >
        FLOOR,
      </if>
      <if test="type != null" >
        TYPE,
      </if>
      <if test="area != null" >
        AREA,
      </if>
      <if test="rate != null" >
        RATE,
      </if>
      <if test="price != null" >
        PRICE,
      </if>
      <if test="vtype != null" >
        VTYPE,
      </if>
      <if test="vroomno != null" >
        VROOMNO,
      </if>
      <if test="v1 != null" >
        V1,
      </if>
      <if test="v2 != null" >
        V2,
      </if>
      <if test="v3 != null" >
        V3,
      </if>
      <if test="v4 != null" >
        V4,
      </if>
      <if test="v5 != null" >
        V5,
      </if>
      <if test="v6 != null" >
        V6,
      </if>
      <if test="v7 != null" >
        V7,
      </if>
      <if test="v8 != null" >
        V8,
      </if>
      <if test="v9 != null" >
        V9,
      </if>
      <if test="v10 != null" >
        V10,
      </if>
    </trim>
    <trim prefix="values (" suffix=")" suffixOverrides="," >
      <if test="id != null" >
        #{id,jdbcType=DECIMAL},
      </if>
      <if test="build != null" >
        #{build,jdbcType=VARCHAR},
      </if>
      <if test="roomno != null" >
        #{roomno,jdbcType=VARCHAR},
      </if>
      <if test="floor != null" >
        #{floor,jdbcType=VARCHAR},
      </if>
      <if test="type != null" >
        #{type,jdbcType=VARCHAR},
      </if>
      <if test="area != null" >
        #{area,jdbcType=DECIMAL},
      </if>
      <if test="rate != null" >
        #{rate,jdbcType=DECIMAL},
      </if>
      <if test="price != null" >
        #{price,jdbcType=DECIMAL},
      </if>
      <if test="vtype != null" >
        #{vtype,jdbcType=VARCHAR},
      </if>
      <if test="vroomno != null" >
        #{vroomno,jdbcType=VARCHAR},
      </if>
      <if test="v1 != null" >
        #{v1,jdbcType=DECIMAL},
      </if>
      <if test="v2 != null" >
        #{v2,jdbcType=DECIMAL},
      </if>
      <if test="v3 != null" >
        #{v3,jdbcType=DECIMAL},
      </if>
      <if test="v4 != null" >
        #{v4,jdbcType=DECIMAL},
      </if>
      <if test="v5 != null" >
        #{v5,jdbcType=DECIMAL},
      </if>
      <if test="v6 != null" >
        #{v6,jdbcType=DECIMAL},
      </if>
      <if test="v7 != null" >
        #{v7,jdbcType=DECIMAL},
      </if>
      <if test="v8 != null" >
        #{v8,jdbcType=DECIMAL},
      </if>
      <if test="v9 != null" >
        #{v9,jdbcType=DECIMAL},
      </if>
      <if test="v10 != null" >
        #{v10,jdbcType=DECIMAL},
      </if>
    </trim>
  </insert>
  <update id="updateByPrimaryKeySelective" parameterType="com.rent.entity.PrhDevTmp2" >
    <!--
      WARNING - @mbggenerated
      This element is automatically generated by MyBatis Generator, do not modify.
      This element was generated on Mon Apr 24 14:56:49 CST 2017.
    -->
    update PRH_DEV_TMP2
    <set >
      <if test="build != null" >
        BUILD = #{build,jdbcType=VARCHAR},
      </if>
      <if test="roomno != null" >
        ROOMNO = #{roomno,jdbcType=VARCHAR},
      </if>
      <if test="floor != null" >
        FLOOR = #{floor,jdbcType=VARCHAR},
      </if>
      <if test="type != null" >
        TYPE = #{type,jdbcType=VARCHAR},
      </if>
      <if test="area != null" >
        AREA = #{area,jdbcType=DECIMAL},
      </if>
      <if test="rate != null" >
        RATE = #{rate,jdbcType=DECIMAL},
      </if>
      <if test="price != null" >
        PRICE = #{price,jdbcType=DECIMAL},
      </if>
      <if test="vtype != null" >
        VTYPE = #{vtype,jdbcType=VARCHAR},
      </if>
      <if test="vroomno != null" >
        VROOMNO = #{vroomno,jdbcType=VARCHAR},
      </if>
      <if test="v1 != null" >
        V1 = #{v1,jdbcType=DECIMAL},
      </if>
      <if test="v2 != null" >
        V2 = #{v2,jdbcType=DECIMAL},
      </if>
      <if test="v3 != null" >
        V3 = #{v3,jdbcType=DECIMAL},
      </if>
      <if test="v4 != null" >
        V4 = #{v4,jdbcType=DECIMAL},
      </if>
      <if test="v5 != null" >
        V5 = #{v5,jdbcType=DECIMAL},
      </if>
      <if test="v6 != null" >
        V6 = #{v6,jdbcType=DECIMAL},
      </if>
      <if test="v7 != null" >
        V7 = #{v7,jdbcType=DECIMAL},
      </if>
      <if test="v8 != null" >
        V8 = #{v8,jdbcType=DECIMAL},
      </if>
      <if test="v9 != null" >
        V9 = #{v9,jdbcType=DECIMAL},
      </if>
      <if test="v10 != null" >
        V10 = #{v10,jdbcType=DECIMAL},
      </if>
    </set>
    where ID = #{id,jdbcType=DECIMAL}
  </update>
  <update id="updateByPrimaryKey" parameterType="com.rent.entity.PrhDevTmp2" >
    <!--
      WARNING - @mbggenerated
      This element is automatically generated by MyBatis Generator, do not modify.
      This element was generated on Mon Apr 24 14:56:49 CST 2017.
    -->
    update PRH_DEV_TMP2
    set BUILD = #{build,jdbcType=VARCHAR},
      ROOMNO = #{roomno,jdbcType=VARCHAR},
      FLOOR = #{floor,jdbcType=VARCHAR},
      TYPE = #{type,jdbcType=VARCHAR},
      AREA = #{area,jdbcType=DECIMAL},
      RATE = #{rate,jdbcType=DECIMAL},
      PRICE = #{price,jdbcType=DECIMAL},
      VTYPE = #{vtype,jdbcType=VARCHAR},
      VROOMNO = #{vroomno,jdbcType=VARCHAR},
      V1 = #{v1,jdbcType=DECIMAL},
      V2 = #{v2,jdbcType=DECIMAL},
      V3 = #{v3,jdbcType=DECIMAL},
      V4 = #{v4,jdbcType=DECIMAL},
      V5 = #{v5,jdbcType=DECIMAL},
      V6 = #{v6,jdbcType=DECIMAL},
      V7 = #{v7,jdbcType=DECIMAL},
      V8 = #{v8,jdbcType=DECIMAL},
      V9 = #{v9,jdbcType=DECIMAL},
      V10 = #{v10,jdbcType=DECIMAL}
    where ID = #{id,jdbcType=DECIMAL}
  </update>
</mapper>